{
    "campFormSlots": [
        {
            "tabPageId": "1",
            "tabSlotId": "S00",
            "status": 0
        },{
            "tabPageId": "1845",
            "tabSlotId": "S22",
            "applyingUserId": "HT31AB",
            "actionName": "pierwsza zgłoszona akcja",
            "actionMatrixId": 2,
            "productGroupId": 3,
            "squadId": 1
        },{
            "tabPageId": "4512",
            "tabSlotId": "S99",
            "status": 0
        }
    ]
}
