{
    "campFormTabs": [
        {
            "tabPageId": "1",
            "tabSlotId": "S00",
            "tabTitle": "Informacja",
            "tabSubtitle": "",
            "tabPageType": "I",
            "tabIndex": 0,
            "tabClose": false,
            "tabActive": true
        },{
            "tabPageId": "1845",
            "tabSlotId": "S22",
            "tabTitle": "Event_BLIK_transakcja_gotowkowa",
            "tabSubtitle": "wersja robocza",
            "tabPageType": "E",
            "tabIndex": 2,
            "tabClose": true,
            "tabActive": false
        },{
            "tabPageId": "4512",
            "tabSlotId": "S98",
            "tabTitle": "Szukanie",
            "tabSubtitle": "zaawansowane",
            "tabPageType": "F",
            "tabIndex": 4,
            "tabClose": true,
            "tabActive": false
        }
    ]
}
